denmune_skl/__init__.py
denmune_skl/_version.py
denmune_skl/denmune.py
denmune_skl/tests/__init__.py
denmune_skl/tests/test_common.py
denmune_skl/tests/test_denmune.py
denmune_skl/utils/__init__.py
denmune_skl/utils/discovery.py
denmune_skl/utils/tests/__init__.py
denmune_skl/utils/tests/test_discovery.py
denmune_skl-0.1.4.dist-info/licenses/LICENSE
denmune_skl-0.1.4.dist-info/METADATA
denmune_skl-0.1.4.dist-info/WHEEL
denmune_skl-0.1.4.dist-info/top_level.txt
denmune_skl-0.1.4.dist-info/RECORD
