Metadata-Version: 2.4
Name: denmune-skl
Version: 0.1.4
Summary: A performant 3rd party implementation of the Denmune Clustering algorithm
Author-email: Loo Jun Zing <jzloo11111@gmail.com>
Project-URL: Homepage, https://github.com/scikit-learn-contrib/denmune-skl
Project-URL: Bug Tracker, https://github.com/scikit-learn-contrib/denmune-skl/issues
Project-URL: Documentation, https://contrib.scikit-learn.org/denmune-skl/
Project-URL: Source Code, https://github.com/scikit-learn-contrib/denmune-skl
Classifier: Intended Audience :: Science/Research
Classifier: Intended Audience :: Developers
Classifier: Programming Language :: Python
Classifier: Topic :: Software Development
Classifier: Topic :: Scientific/Engineering
Classifier: Programming Language :: Python :: 3
Classifier: Programming Language :: Python :: 3.9
Classifier: Programming Language :: Python :: 3.10
Classifier: Programming Language :: Python :: 3.11
Classifier: Programming Language :: Python :: 3.12
Classifier: Programming Language :: Python :: 3.13
Classifier: License :: OSI Approved :: BSD License
Classifier: Operating System :: POSIX
Classifier: Operating System :: Unix
Classifier: Operating System :: MacOS
Classifier: Operating System :: Microsoft :: Windows
Requires-Python: >=3.9
License-File: LICENSE
Requires-Dist: numpy
Requires-Dist: scipy
Requires-Dist: scikit-learn
Dynamic: license-file
